mcp_lightpdf/__init__.py
mcp_lightpdf/common.py
mcp_lightpdf/converter.py
mcp_lightpdf/editor.py
mcp_lightpdf/server.py
mcp_lightpdf-0.1.30.dist-info/METADATA
mcp_lightpdf-0.1.30.dist-info/WHEEL
mcp_lightpdf-0.1.30.dist-info/entry_points.txt
mcp_lightpdf-0.1.30.dist-info/top_level.txt
mcp_lightpdf-0.1.30.dist-info/RECORD
