Metadata-Version: 2.4
Name: mcp_lightpdf
Version: 0.1.30
Summary: LightPDF AI助手 MCP Server
Requires-Python: >=3.12
Requires-Dist: mcp
Requires-Dist: httpx
Requires-Dist: python-dotenv
